benchmark_apis/__init__.py
repo_template-0.0.1.dist-info/LICENSE
repo_template-0.0.1.dist-info/METADATA
repo_template-0.0.1.dist-info/WHEEL
repo_template-0.0.1.dist-info/top_level.txt
repo_template-0.0.1.dist-info/RECORD
